Jeevatech_STT/__init__.py
jeeva_stt-0.1.dist-info/METADATA
jeeva_stt-0.1.dist-info/WHEEL
jeeva_stt-0.1.dist-info/top_level.txt
jeeva_stt-0.1.dist-info/RECORD
