Metadata-Version: 2.4
Name: Jeeva_STT
Version: 0.1
Summary: this is stt pack create by a rajveer
Author: Rajveer Singh Chouhan
Author-email: chouhanrajveer009@gmail.com
Dynamic: author
Dynamic: author-email
Dynamic: summary
